MANIFEST.in
README.rst
setup.cfg
setup.py
docs/Makefile
docs/conf.py
docs/index.rst
docs/main.rst
docs/make.bat
docs/screenshots/printtemplate.png
docs/screenshots/printtemplate_print.png
ringo_printtemplate/__init__.py
ringo_printtemplate/model.py
ringo_printtemplate/odfconv.py
ringo_printtemplate/print.xml
ringo_printtemplate/printtemplates.json
ringo_printtemplate/printtemplates.xml
ringo_printtemplate/views.py
ringo_printtemplate.egg-info/PKG-INFO
ringo_printtemplate.egg-info/SOURCES.txt
ringo_printtemplate.egg-info/dependency_links.txt
ringo_printtemplate.egg-info/entry_points.txt
ringo_printtemplate.egg-info/not-zip-safe
ringo_printtemplate.egg-info/requires.txt
ringo_printtemplate.egg-info/top_level.txt
ringo_printtemplate/lib/__init__.py
ringo_printtemplate/lib/renderer.py
ringo_printtemplate/locale/ringo_printtemplate.pot
ringo_printtemplate/locale/de/LC_MESSAGES/ringo_printtemplate.po
ringo_printtemplate/templates/internal/print.mako