Metadata-Version: 1.0
Name: ringo-printtemplate
Version: 1.2
Summary: Extension for printtemplates in the ringo webframework
Home-page: https://github.com/ringo-framework/ringo_printtemplates
Author: Torsten Irländer
Author-email: torsten.irlaender@googlemail.com
License: MIT
Keywords: ringo pyramid extension
Platform: UNKNOWN
